<?xml version="1.0" encoding="UTF-8"?>
<!-- edited with XMLSPY v2004 rel. 3 U (http://www.xmlspy.com) by IMCGames Co., Ltd (IMCGames Co., Ltd) -->
<ActionDesc>
    <Shockwave frame="0" type="2" intensity="3" frequency="70" duration="2.3" range="1000"/>
    <BlendOn frame="0" R="0" G="0" B="0" A="50"/>
    <Particle frame="0" attachNode="Dummy_emitter_pet" particleName="I_smoke014_5" useAttach="true" hiddenObj="false" changeEffect="None" scale="3" pause="true" use2DEffect="false" soft2DValue="20" targetPos="false"/>
    <Particle frame="0" attachNode="Dummy_emitter_pet" particleName="I_dash035_green" useAttach="true" hiddenObj="false" changeEffect="None" scale="2.5" pause="true" use2DEffect="false" soft2DValue="20" targetPos="false"/>
    <Particle frame="0" attachNode="Dummy_emitter_pet3" particleName="I_dash022_1_green" useAttach="true" hiddenObj="false" changeEffect="None" scale="2" pause="true" use2DEffect="false" soft2DValue="20" targetPos="false"/>
    <BlendOn frame="6" R="100" G="200" B="100" A="100"/>
    <Particle frame="6" attachNode="Dummy_effect_pistol001_ride" particleName="I_archer_pistol_atk_green" useAttach="true" hiddenObj="false" changeEffect="None" scale="3" pause="true" use2DEffect="true" soft2DValue="20" targetPos="false"/>
    <BlendOn frame="7" R="0" G="0" B="0" A="50"/>
    <BlendOn frame="11" R="100" G="150" B="200" A="100"/>
    <Particle frame="11" attachNode="Dummy_effect_pistol001_ride" particleName="I_archer_pistol_atk_green" useAttach="true" hiddenObj="false" changeEffect="None" scale="3" pause="true" use2DEffect="true" soft2DValue="20" targetPos="false"/>
    <BlendOn frame="12" R="0" G="0" B="0" A="50"/>
    <Particle frame="15" attachNode="Dummy_emitter_pet" particleName="I_dash035_green" useAttach="true" hiddenObj="false" changeEffect="None" scale="2.5" pause="true" use2DEffect="false" soft2DValue="20" targetPos="false"/>
    <Particle frame="15" attachNode="Dummy_emitter_pet3" particleName="I_dash022_1_green" useAttach="true" hiddenObj="false" changeEffect="None" scale="2" pause="true" use2DEffect="false" soft2DValue="20" targetPos="false"/>
    <BlendOn frame="16" R="100" G="200" B="100" A="100"/>
    <Particle frame="16" attachNode="Dummy_effect_pistol001_ride" particleName="I_archer_pistol_atk_green" useAttach="true" hiddenObj="false" changeEffect="None" scale="3" pause="true" use2DEffect="true" soft2DValue="20" targetPos="false"/>
    <BlendOn frame="17" R="0" G="0" B="0" A="50"/>
    <Particle frame="20" attachNode="Dummy_emitter_pet" particleName="I_smoke014_5" useAttach="true" hiddenObj="false" changeEffect="None" scale="2.5" pause="true" use2DEffect="false" soft2DValue="20" targetPos="false"/>
    <BlendOn frame="21" R="100" G="150" B="200" A="100"/>
    <Particle frame="21" attachNode="Dummy_effect_pistol001_ride" particleName="I_archer_pistol_atk_green" useAttach="true" hiddenObj="false" changeEffect="None" scale="3" pause="true" use2DEffect="true" soft2DValue="20" targetPos="false"/>
    <BlendOn frame="22" R="0" G="0" B="0" A="50"/>
    <BlendOn frame="26" R="100" G="200" B="100" A="100"/>
    <Particle frame="26" attachNode="Dummy_effect_pistol001_ride" particleName="I_archer_pistol_atk_green" useAttach="true" hiddenObj="false" changeEffect="None" scale="3" pause="true" use2DEffect="true" soft2DValue="20" targetPos="false"/>
    <BlendOn frame="27" R="0" G="0" B="0" A="50"/>
    <Particle frame="30" attachNode="Dummy_emitter_pet" particleName="I_smoke014_5" useAttach="true" hiddenObj="false" changeEffect="None" scale="2" pause="true" use2DEffect="false" soft2DValue="20" targetPos="false"/>
    <Particle frame="30" attachNode="Dummy_emitter_pet" particleName="I_dash035_green" useAttach="true" hiddenObj="false" changeEffect="None" scale="2.5" pause="true" use2DEffect="false" soft2DValue="20" targetPos="false"/>
    <Particle frame="30" attachNode="Dummy_emitter_pet3" particleName="I_dash022_1_green" useAttach="true" hiddenObj="false" changeEffect="None" scale="2" pause="true" use2DEffect="false" soft2DValue="20" targetPos="false"/>
    <BlendOn frame="31" R="100" G="150" B="200" A="100"/>
    <Particle frame="31" attachNode="Dummy_effect_pistol001_ride" particleName="I_archer_pistol_atk_green" useAttach="true" hiddenObj="false" changeEffect="None" scale="3" pause="true" use2DEffect="true" soft2DValue="20" targetPos="false"/>
    <BlendOn frame="32" R="0" G="0" B="0" A="50"/>
    <Particle frame="35" attachNode="Dummy_emitter_pet" particleName="I_smoke014_5" useAttach="true" hiddenObj="false" changeEffect="None" scale="2" pause="true" use2DEffect="false" soft2DValue="20" targetPos="false"/>
    <BlendOn frame="37" R="100" G="200" B="100" A="100"/>
    <Particle frame="37" attachNode="Dummy_effect_pistol001_ride" particleName="I_archer_pistol_atk_green" useAttach="true" hiddenObj="false" changeEffect="None" scale="4" pause="true" use2DEffect="true" soft2DValue="20" targetPos="false"/>
    <BlendOn frame="38" R="80" G="180" B="80" A="100"/>
    <BlendOn frame="39" R="50" G="150" B="50" A="100"/>
    <BlendOn frame="40" R="30" G="130" B="30" A="100"/>
    <BlendOn frame="41" R="0" G="0" B="0" A="50"/>
    <BlendOff frame="42" R="0" G="0" B="0" A="0"/>
</ActionDesc>
