<?xml version="1.0" encoding="UTF-8"?>
<GameList>
    <Game Name="CHALLENGE_AUTO_1" minLv="0" maxLv="0" mapName="Challenge_d_firetower_69_2" playerCountCheckDestroy="1" startWaitSec="-1">
        <StageList>
            <Stage Name="Start">
                <ObjList>
                    <Obj Type="Monster" MonType="20025" Pos="2.55#89.09#1160.19" genCount="1" genTime="20000" objectKey="0"/>
                </ObjList>
                <StageEvents>
                    <Event eventName="ChallengeStart">
                        <condList>
                            <ToolScp Scp="GAME_ST_EVT_COND_VALUE" Client="NO" UseSleep="NO">
                                <Str Str="is_start_auto_challenge"/>
                                <Str Str="=="/>
                                <Num Num="0"/>
                            </ToolScp>
                        </condList>
                        <execList>
                            <ToolScp Scp="MGAME_EVT_SCP_TO_MON_CMD" Client="NO" UseSleep="NO">
                                <MGameObj List="Start/0"/>
                                <Str Str="SCR_AUTO_CHALLENGE_START"/>
                            </ToolScp>
                        </execList>
                    </Event>
                    <Event eventName="GenMonster">
                        <condList>
                            <ToolScp Scp="GAME_ST_EVT_COND_VALUE" Client="NO" UseSleep="NO">
                                <Str Str="is_start_auto_challenge"/>
                                <Str Str="=="/>
                                <Num Num="1"/>
                            </ToolScp>
                        </condList>
                        <execList>
                            <ToolScp Scp="MGAME_EVT_SCP_TO_MON_CMD" Client="NO" UseSleep="NO">
                                <MGameObj List="Start/0"/>
                                <Str Str="SCR_AUTO_CHALLENGE_GEN_MONSTER"/>
                            </ToolScp>
                        </execList>
                    </Event>
                    <Event eventName="GenBoss">
                        <condList>
                            <ToolScp Scp="SCR_MGAME_VALUE_CHECK_2" Client="NO" UseSleep="NO">
                                <Str Str="is_start_auto_challenge"/>
                                <Str Str="=="/>
                                <Num Num="1"/>
                            </ToolScp>
                            <ToolScp Scp="SCR_MGAME_VALUE_CHECK_2" Client="NO" UseSleep="NO">
                                <Str Str="is_start_boss_auto_challenge"/>
                                <Str Str="EQ"/>
                                <Num Num="1"/>
                            </ToolScp>
                        </condList>
                        <execList>
                            <ToolScp Scp="MGAME_EVT_SCP_TO_MON_CMD" Client="NO" UseSleep="NO">
                                <MGameObj List="Start/0"/>
                                <Str Str="SCR_AUTO_CHALLENGE_GEN_BOSS_MONSTER"/>
                            </ToolScp>
                        </execList>
                    </Event>
                    <Event execCount="1" eventName="Ready">
                        <condList>
                            <ToolScp Scp="GAME_ST_EVT_COND_VALUE" Client="NO" UseSleep="NO">
                                <Str Str="is_start_auto_challenge"/>
                                <Str Str="=="/>
                                <Num Num="1"/>
                            </ToolScp>
                        </condList>
                        <execList>
                            <ToolScp Scp="MGAME_EVT_SCP_TO_MON_CMD" Client="NO" UseSleep="NO">
                                <MGameObj List="Start/0"/>
                                <Str Str="SCR_AUTO_CHALLENGE_GEN_MONSTER_READY"/>
                            </ToolScp>
                        </execList>
                    </Event>
                    <Event eventName="Update">
                        <condList>
                            <ToolScp Scp="GAME_ST_EVT_COND_VALUE" Client="NO" UseSleep="NO">
                                <Str Str="is_start_auto_challenge"/>
                                <Str Str="=="/>
                                <Num Num="1"/>
                            </ToolScp>
                        </condList>
                        <execList>
                            <ToolScp Scp="MGAME_EVT_SCP_TO_MON_CMD" Client="NO" UseSleep="NO">
                                <MGameObj List="Start/0"/>
                                <Str Str="SCR_AUTO_CHALLENGE_UPDATE"/>
                            </ToolScp>
                        </execList>
                    </Event>
                    <Event execCount="1" eventName="AutoPartyBuff">
                        <condList>
                            <ToolScp Scp="MGAME_EVT_COND_PCCNT_OVER" Client="NO" UseSleep="NO">
                                <Num Num="1"/>
                            </ToolScp>
                            <ToolScp Scp="GAME_ST_EVT_COND_VALUE" Client="NO" UseSleep="NO">
                                <Str Str="is_start_auto_challenge"/>
                                <Str Str="=="/>
                                <Num Num="0"/>
                            </ToolScp>
                        </condList>
                        <execList>
                            <ToolScp Scp="MGAME_EXEC_SELECT_BUFF_PARTY" Client="NO" UseSleep="NO">
                                <Num Num="20"/>
                                <Str Str="AUTO_MATCHING_PARTY_ATTACK_BUFF"/>
                                <Str Str="AUTO_MATCHING_PARTY_DEFENCE_BUFF"/>
                                <Str Str="AUTO_MATCHING_PARTY_HEAL_BUFF"/>
                                <Str Str="AUTO_MATCHING_PARTY_HEAL2_BUFF"/>
                                <Str Str="None"/>
                                <Num Num="2"/>
                            </ToolScp>
                        </execList>
                    </Event>
                    <Event execMS="60000" eventName="GenObject">
                        <condList>
                            <ToolScp Scp="GAME_ST_EVT_COND_VALUE" Client="NO" UseSleep="NO">
                                <Str Str="is_start_auto_challenge"/>
                                <Str Str="=="/>
                                <Num Num="1"/>
                            </ToolScp>
                        </condList>
                        <execList>
                            <ToolScp Scp="MGAME_EVT_SCP_TO_MON_CMD" Client="NO" UseSleep="NO">
                                <MGameObj List="Start/0"/>
                                <Str Str="SCR_AUTO_CHALLENGE_GEN_OBJECT_INIT_SETTING"/>
                            </ToolScp>
                        </execList>
                    </Event>
                    <Event execMS="1500" eventName="GenObjectStart">
                        <condList>
                            <ToolScp Scp="GAME_ST_EVT_COND_VALUE" Client="NO" UseSleep="NO">
                                <Str Str="is_start_auto_challenge"/>
                                <Str Str="=="/>
                                <Num Num="1"/>
                            </ToolScp>
                            <ToolScp Scp="GAME_ST_EVT_COND_VALUE" Client="NO" UseSleep="NO">
                                <Str Str="gen_object_start"/>
                                <Str Str="=="/>
                                <Num Num="1"/>
                            </ToolScp>
                        </condList>
                        <execList>
                            <ToolScp Scp="MGAME_EVT_SCP_TO_MON_CMD" Client="NO" UseSleep="NO">
                                <MGameObj List="Start/0"/>
                                <Str Str="SCR_AUTO_CHALLENGE_GEN_OBJECT_START"/>
                            </ToolScp>
                        </execList>
                    </Event>
                </StageEvents>
            </Stage>
            <Stage Name="End" AutoStart="0">
                <ObjList/>
                <StageEvents>
                    <Event execCount="1" eventName="Reward">
                        <condList>
                            <ToolScp Scp="MGAME_EVT_COND_PCCNT_OVER" Client="NO" UseSleep="NO">
                                <Num Num="1"/>
                            </ToolScp>
                            <ToolScp Scp="GAME_ST_EVT_COND_VALUE" Client="NO" UseSleep="NO">
                                <Str Str="is_kill_boss_state"/>
                                <Str Str="=="/>
                                <Num Num="1"/>
                            </ToolScp>
                        </condList>
                        <execList>
                            <ToolScp Scp="GAME_ST_EVT_EXEC_STAGE_DISABLE" Client="NO" UseSleep="NO">
                                <Str Str="Start"/>
                            </ToolScp>
                            <ToolScp Scp="MGAME_EVT_SCP_TO_MON_CMD" Client="NO" UseSleep="NO">
                                <MGameObj List="Start/0"/>
                                <Str Str="SCR_AUTO_CHALLENGE_COMPLETE"/>
                            </ToolScp>
                            <ToolScp Scp="MGAME_EVT_SCP_TO_MON_CMD" Client="NO" UseSleep="NO">
                                <MGameObj List="Start/0"/>
                                <Str Str="SCR_AUTO_CHALLENGE_REWARD"/>
                            </ToolScp>
                            <ToolScp Scp="MGAME_EVT_SCP_TO_MON_CMD" Client="NO" UseSleep="NO">
                                <MGameObj List="Start/0"/>
                                <Str Str="SCR_AUTO_CHALLENGE_END"/>
                            </ToolScp>
                        </execList>
                    </Event>
                    <Event execCount="1" eventName="Fail">
                        <condList>
                            <ToolScp Scp="MGAME_EVT_COND_PCCNT_OVER" Client="NO" UseSleep="NO">
                                <Num Num="1"/>
                            </ToolScp>
                            <ToolScp Scp="GAME_ST_EVT_COND_VALUE" Client="NO" UseSleep="NO">
                                <Str Str="is_kill_boss_state"/>
                                <Str Str="=="/>
                                <Num Num="0"/>
                            </ToolScp>
                        </condList>
                        <execList>
                            <ToolScp Scp="GAME_ST_EVT_EXEC_STAGE_DISABLE" Client="NO" UseSleep="NO">
                                <Str Str="Start"/>
                            </ToolScp>
                            <ToolScp Scp="MGAME_EVT_SCP_TO_MON_CMD" Client="NO" UseSleep="NO">
                                <MGameObj List="Start/0"/>
                                <Str Str="SCR_AUTO_CHALLENGE_END"/>
                            </ToolScp>
                        </execList>
                    </Event>
                    <Event execCount="1" eventName="Return_Zone">
                        <condList>
                            <ToolScp Scp="GAME_ST_EVT_COND_TIMECHECK" Client="NO" UseSleep="NO">
                                <Num Num="20"/>
                            </ToolScp>
                        </condList>
                        <execList>
                            <ToolScp Scp="MGAME_END" Client="NO" UseSleep="NO">
                                <Num Num="1"/>
                            </ToolScp>
                            <ToolScp Scp="MGAME_RETURN" Client="NO" UseSleep="NO"/>
                        </execList>
                    </Event>
                    <Event execCount="1" eventName="10Sec">
                        <condList>
                            <ToolScp Scp="GAME_ST_EVT_COND_TIMECHECK" Client="NO" UseSleep="NO">
                                <Num Num="10"/>
                            </ToolScp>
                        </condList>
                        <execList>
                            <ToolScp Scp="MGAME_MSG_ICON" Client="YES" UseSleep="NO">
                                <Str Str="10초 후 입장 지역으로 돌아갑니다."/>
                                <Str Str="!"/>
                                <Num Num="5"/>
                            </ToolScp>
                        </execList>
                    </Event>
                </StageEvents>
            </Stage>
        </StageList>
        <EnterList>
            <ToolScp Scp="MGAME_ZONEENTER_SCRIPT" Client="NO" UseSleep="NO">
                <Num Num="2"/>
                <Str Str="SCR_AUTO_CHALLENGE_RESTART"/>
            </ToolScp>
            <ToolScp Scp="MGAME_ZONE_ENTER_SELECT_BUFF_SOLO" Client="NO" UseSleep="NO">
                <Num Num="20"/>
                <Str Str="AUTO_MATCHING_ADD_SR_BUFF"/>
                <Str Str="AUTO_MATCHING_DARK_SPHERE_BUFF"/>
                <Str Str="AUTO_MATCHING_SPLIT_BUFF"/>
                <Str Str="AUTO_MATCHING_CROWD_CONTROL_BUFF"/>
                <Str Str="AUTO_MATCHING_TANKER_BUFF"/>
                <Num Num="2"/>
            </ToolScp>
        </EnterList>
    </Game>
</GameList>
